LICENSE
README.md
setup.py
eqsmart/__init__.py
eqsmart.egg-info/PKG-INFO
eqsmart.egg-info/SOURCES.txt
eqsmart.egg-info/dependency_links.txt
eqsmart.egg-info/requires.txt
eqsmart.egg-info/top_level.txt
eqsmart/components/__init__.py
eqsmart/components/load_conf.py
eqsmart/components/protocol.py
eqsmart/components/read_conf.py
eqsmart/components/read_module.py
eqsmart/components/scan_services.py
eqsmart/main/__init__.py
eqsmart/main/consumer.py
eqsmart/main/http_servr.py
eqsmart/main/provider.py
eqsmart/main/remote_call.py